iplens/__init__.py
iplens/base_operations.py
iplens/config.cfg
iplens/config_loader.py
iplens/db_cache.py
iplens/input_processor.py
iplens/ipapi_api.py
iplens/iplens_cli.py
iplens/logger.py
iplens/output.py
iplens/table_formatter.py
iplens/utils.py
iplens-0.2.0.dist-info/METADATA
iplens-0.2.0.dist-info/WHEEL
iplens-0.2.0.dist-info/entry_points.txt
iplens-0.2.0.dist-info/top_level.txt
iplens-0.2.0.dist-info/RECORD
