Metadata-Version: 2.1
Name: iplens
Version: 0.2.0
Summary: A lightweight, modern, robust IP info CLI tool
Home-page: https://github.com/aiomorphic/iplens
Author: aiomorphic
Author-email: iplens@proton.me
Classifier: Development Status :: 3 - Alpha
Classifier: Intended Audience :: Developers
Classifier: License :: OSI Approved :: MIT License
Classifier: Operating System :: OS Independent
Classifier: Programming Language :: Python :: 3
Classifier: Programming Language :: Python :: 3.7
Classifier: Programming Language :: Python :: 3.8
Classifier: Programming Language :: Python :: 3.9
Classifier: Programming Language :: Python :: 3.10
Requires-Python: >=3.7
Requires-Dist: requests <3.0.0,>=2.25.1
Requires-Dist: rich <11.0.0,>=10.0.0
